{
  "generated_at": "2026-05-18T00:54:06.453210+08:00",
  "total_titles_processed": 314,
  "failed_sources": [],
  "trends": [
    {
      "keyword_group": "特朗普",
      "match_count": 5,
      "titles": [
        {
          "title": "美国参议员格雷厄姆敦促特朗普恢复对伊朗的打击",
          "url": "https://flash.jin10.com/detail/20260518001435288800",
          "source": "金十数据",
          "ranks": [
            3
          ],
          "is_new": true,
          "appearance_count": 1,
          "time_info": "00时54分"
        },
        {
          "title": "特朗普访华后续观察",
          "url": "https://www.douyin.com/hot/2502108",
          "source": "抖音",
          "ranks": [
            11
          ],
          "is_new": false,
          "appearance_count": 2,
          "time_info": "[00时53分 ~ 00时54分]"
        },
        {
          "title": "岛内称特朗普警告“台独”重击赖当局",
          "url": "https://www.toutiao.com/trending/7640276210946179115/",
          "source": "今日头条",
          "ranks": [
            14
          ],
          "is_new": false,
          "appearance_count": 2,
          "time_info": "[00时53分 ~ 00时54分]"
        },
        {
          "title": "特朗普刚结束访华，普京便宣布访华，为什么选在这个时间？背后可能有哪些深意？",
          "url": "https://www.zhihu.com/question/2039007666429583394",
          "source": "知乎",
          "ranks": [
            19
          ],
          "is_new": false,
          "appearance_count": 2,
          "time_info": "[00时53分 ~ 00时54分]"
        },
        {
          "title": "据AXIOS：以色列官员透露，特朗普已与以色列总理内塔尼亚胡通电话，并讨论了伊朗问题。",
          "url": "https://flash.jin10.com/detail/20260517233453161800",
          "source": "金十数据",
          "ranks": [
            15
          ],
          "is_new": true,
          "appearance_count": 1,
          "time_info": "00时54分"
        }
      ]
    },
    {
      "keyword_group": "美元",
      "match_count": 3,
      "titles": [
        {
          "title": "27年前捐5000美元植树的美国人找到了",
          "url": "https://www.baidu.com/s?wd=27%E5%B9%B4%E5%89%8D%E6%8D%905000%E7%BE%8E%E5%85%83%E6%A4%8D%E6%A0%91%E7%9A%84%E7%BE%8E%E5%9B%BD%E4%BA%BA%E6%89%BE%E5%88%B0%E4%BA%86",
          "source": "百度热搜",
          "ranks": [
            8
          ],
          "is_new": false,
          "appearance_count": 2,
          "time_info": "[00时53分 ~ 00时54分]"
        },
        {
          "title": "50-100亿美元！“全球最大资管”贝莱德考虑投资“历史最大IPO”Space X",
          "url": "https://wallstreetcn.com/articles/3772438",
          "source": "华尔街见闻",
          "ranks": [
            9
          ],
          "is_new": false,
          "appearance_count": 2,
          "time_info": "[00时53分 ~ 00时54分]"
        },
        {
          "title": "如何看待央视最终以 6500 万美元获得世界杯转播权?",
          "url": "https://www.zhihu.com/question/2038657177729102743",
          "source": "知乎",
          "ranks": [
            13
          ],
          "is_new": false,
          "appearance_count": 2,
          "time_info": "[00时53分 ~ 00时54分]"
        }
      ]
    }
  ],
  "report_image_url": "https://joyce677.github.io/TrendRadar/img/news.jpg"
}